<?xml version='1.0' encoding='ISO-8859-1'?>
<?xml-stylesheet type='text/xsl' href='image_metadata_stylesheet.xsl'?>
<dataset>
<name>Image Set</name>
<images>
  <image file='/Users/lisad/rproj/debruine/webmorphR/images/f_multi.jpg'>
    <box top='180' left='159' width='186' height='186'>
      <part name='000' x='211' y='226'/>
      <part name='001' x='288' y='226'/>
      <part name='002' x='211' y='222'/>
      <part name='003' x='205' y='223'/>
      <part name='004' x='203' y='227'/>
      <part name='005' x='205' y='231'/>
      <part name='006' x='211' y='233'/>
      <part name='007' x='216' y='231'/>
      <part name='008' x='218' y='227'/>
      <part name='009' x='217' y='224'/>
      <part name='010' x='288' y='221'/>
      <part name='011' x='282' y='223'/>
      <part name='012' x='281' y='227'/>
      <part name='013' x='283' y='231'/>
      <part name='014' x='288' y='233'/>
      <part name='015' x='294' y='231'/>
      <part name='016' x='296' y='227'/>
      <part name='017' x='294' y='223'/>
      <part name='018' x='195' y='229'/>
      <part name='019' x='202' y='224'/>
      <part name='020' x='211' y='222'/>
      <part name='021' x='220' y='225'/>
      <part name='022' x='228' y='231'/>
      <part name='023' x='271' y='231'/>
      <part name='024' x='279' y='225'/>
      <part name='025' x='288' y='221'/>
      <part name='026' x='298' y='224'/>
      <part name='027' x='304' y='229'/>
      <part name='028' x='201' y='233'/>
      <part name='029' x='211' y='234'/>
      <part name='030' x='220' y='233'/>
      <part name='031' x='280' y='232'/>
      <part name='032' x='289' y='234'/>
      <part name='033' x='298' y='232'/>
      <part name='034' x='191' y='223'/>
      <part name='035' x='199' y='218'/>
      <part name='036' x='209' y='216'/>
      <part name='037' x='219' y='218'/>
      <part name='038' x='226' y='224'/>
      <part name='039' x='273' y='224'/>
      <part name='040' x='280' y='218'/>
      <part name='041' x='289' y='216'/>
      <part name='042' x='299' y='217'/>
      <part name='043' x='307' y='222'/>
      <part name='044' x='206' y='253'/>
      <part name='045' x='220' y='248'/>
      <part name='046' x='229' y='239'/>
      <part name='047' x='270' y='239'/>
      <part name='048' x='280' y='248'/>
      <part name='049' x='294' y='254'/>
      <part name='050' x='241' y='221'/>
      <part name='051' x='244' y='231'/>
      <part name='052' x='244' y='242'/>
      <part name='053' x='243' y='252'/>
      <part name='054' x='241' y='263'/>
      <part name='055' x='250' y='281'/>
      <part name='056' x='258' y='221'/>
      <part name='057' x='256' y='232'/>
      <part name='058' x='256' y='242'/>
      <part name='059' x='257' y='252'/>
      <part name='060' x='259' y='263'/>
      <part name='061' x='230' y='262'/>
      <part name='062' x='227' y='270'/>
      <part name='063' x='227' y='277'/>
      <part name='064' x='234' y='281'/>
      <part name='065' x='234' y='276'/>
      <part name='066' x='270' y='263'/>
      <part name='067' x='273' y='270'/>
      <part name='068' x='273' y='277'/>
      <part name='069' x='266' y='281'/>
      <part name='070' x='266' y='276'/>
      <part name='071' x='179' y='214'/>
      <part name='072' x='186' y='202'/>
      <part name='073' x='197' y='197'/>
      <part name='074' x='213' y='198'/>
      <part name='075' x='231' y='206'/>
      <part name='076' x='231' y='211'/>
      <part name='077' x='267' y='211'/>
      <part name='078' x='267' y='205'/>
      <part name='079' x='286' y='197'/>
      <part name='080' x='300' y='196'/>
      <part name='081' x='313' y='201'/>
      <part name='082' x='322' y='213'/>
      <part name='083' x='193' y='204'/>
      <part name='084' x='210' y='206'/>
      <part name='085' x='287' y='205'/>
      <part name='086' x='303' y='203'/>
      <part name='087' x='219' y='310'/>
      <part name='088' x='231' y='302'/>
      <part name='089' x='242' y='297'/>
      <part name='090' x='250' y='299'/>
      <part name='091' x='260' y='297'/>
      <part name='092' x='271' y='302'/>
      <part name='093' x='281' y='309'/>
      <part name='094' x='231' y='309'/>
      <part name='095' x='241' y='308'/>
      <part name='096' x='250' y='308'/>
      <part name='097' x='260' y='308'/>
      <part name='098' x='270' y='308'/>
      <part name='099' x='231' y='309'/>
      <part name='100' x='241' y='308'/>
      <part name='101' x='251' y='309'/>
      <part name='102' x='260' y='308'/>
      <part name='103' x='270' y='308'/>
      <part name='104' x='228' y='317'/>
      <part name='105' x='239' y='321'/>
      <part name='106' x='251' y='323'/>
      <part name='107' x='264' y='321'/>
      <part name='108' x='274' y='316'/>
      <part name='109' x='164' y='231'/>
      <part name='110' x='166' y='258'/>
      <part name='111' x='171' y='288'/>
      <part name='112' x='335' y='229'/>
      <part name='113' x='334' y='257'/>
      <part name='114' x='329' y='287'/>
      <part name='115' x='150' y='225'/>
      <part name='116' x='148' y='241'/>
      <part name='117' x='152' y='259'/>
      <part name='118' x='156' y='276'/>
      <part name='119' x='164' y='288'/>
      <part name='120' x='349' y='223'/>
      <part name='121' x='352' y='238'/>
      <part name='122' x='348' y='256'/>
      <part name='123' x='345' y='272'/>
      <part name='124' x='338' y='286'/>
      <part name='125' x='176' y='309'/>
      <part name='126' x='187' y='331'/>
      <part name='127' x='205' y='348'/>
      <part name='128' x='227' y='359'/>
      <part name='129' x='252' y='364'/>
      <part name='130' x='277' y='358'/>
      <part name='131' x='297' y='346'/>
      <part name='132' x='314' y='329'/>
      <part name='133' x='324' y='308'/>
      <part name='134' x='168' y='203'/>
      <part name='135' x='176' y='179'/>
      <part name='136' x='184' y='157'/>
      <part name='137' x='199' y='141'/>
      <part name='138' x='222' y='132'/>
      <part name='139' x='249' y='130'/>
      <part name='140' x='276' y='132'/>
      <part name='141' x='298' y='141'/>
      <part name='142' x='314' y='158'/>
      <part name='143' x='323' y='180'/>
      <part name='144' x='331' y='202'/>
      <part name='145' x='190' y='369'/>
      <part name='146' x='150' y='311'/>
      <part name='147' x='136' y='228'/>
      <part name='148' x='146' y='177'/>
      <part name='149' x='168' y='136'/>
      <part name='150' x='201' y='106'/>
      <part name='151' x='250' y='94'/>
      <part name='152' x='302' y='108'/>
      <part name='153' x='334' y='140'/>
      <part name='154' x='355' y='178'/>
      <part name='155' x='365' y='227'/>
      <part name='156' x='351' y='309'/>
      <part name='157' x='314' y='367'/>
      <part name='158' x='221' y='280'/>
      <part name='159' x='214' y='290'/>
      <part name='160' x='209' y='301'/>
      <part name='161' x='281' y='280'/>
      <part name='162' x='288' y='290'/>
      <part name='163' x='293' y='302'/>
      <part name='164' x='175' y='251'/>
      <part name='165' x='187' y='262'/>
      <part name='166' x='204' y='267'/>
      <part name='167' x='325' y='251'/>
      <part name='168' x='314' y='262'/>
      <part name='169' x='299' y='267'/>
      <part name='170' x='244' y='283'/>
      <part name='171' x='242' y='293'/>
      <part name='172' x='257' y='283'/>
      <part name='173' x='259' y='293'/>
      <part name='174' x='251' y='341'/>
      <part name='175' x='252' y='351'/>
      <part name='176' x='237' y='333'/>
      <part name='177' x='251' y='330'/>
      <part name='178' x='265' y='333'/>
      <part name='179' x='244' y='277'/>
      <part name='180' x='246' y='280'/>
      <part name='181' x='254' y='280'/>
      <part name='182' x='256' y='276'/>
      <part name='183' x='226' y='391'/>
      <part name='184' x='278' y='392'/>
      <part name='185' x='164' y='245'/>
      <part name='186' x='168' y='273'/>
      <part name='187' x='335' y='243'/>
      <part name='188' x='332' y='272'/>
    </box>
  </image>
  <image file='/Users/lisad/rproj/debruine/webmorphR/images/m_multi.jpg'>
    <box top='160' left='159' width='186' height='185'>
      <part name='000' x='211' y='214'/>
      <part name='001' x='286' y='216'/>
      <part name='002' x='211' y='210'/>
      <part name='003' x='205' y='212'/>
      <part name='004' x='204' y='215'/>
      <part name='005' x='206' y='219'/>
      <part name='006' x='211' y='221'/>
      <part name='007' x='216' y='219'/>
      <part name='008' x='218' y='215'/>
      <part name='009' x='217' y='212'/>
      <part name='010' x='286' y='211'/>
      <part name='011' x='281' y='213'/>
      <part name='012' x='280' y='216'/>
      <part name='013' x='281' y='220'/>
      <part name='014' x='287' y='222'/>
      <part name='015' x='292' y='220'/>
      <part name='016' x='294' y='216'/>
      <part name='017' x='292' y='213'/>
      <part name='018' x='196' y='217'/>
      <part name='019' x='202' y='212'/>
      <part name='020' x='211' y='210'/>
      <part name='021' x='220' y='213'/>
      <part name='022' x='228' y='219'/>
      <part name='023' x='269' y='220'/>
      <part name='024' x='278' y='214'/>
      <part name='025' x='286' y='211'/>
      <part name='026' x='295' y='214'/>
      <part name='027' x='301' y='219'/>
      <part name='028' x='203' y='220'/>
      <part name='029' x='211' y='222'/>
      <part name='030' x='220' y='220'/>
      <part name='031' x='278' y='221'/>
      <part name='032' x='287' y='222'/>
      <part name='033' x='295' y='221'/>
      <part name='034' x='192' y='213'/>
      <part name='035' x='200' y='208'/>
      <part name='036' x='209' y='206'/>
      <part name='037' x='219' y='207'/>
      <part name='038' x='227' y='211'/>
      <part name='039' x='271' y='212'/>
      <part name='040' x='279' y='208'/>
      <part name='041' x='288' y='207'/>
      <part name='042' x='298' y='209'/>
      <part name='043' x='306' y='214'/>
      <part name='044' x='207' y='240'/>
      <part name='045' x='220' y='235'/>
      <part name='046' x='230' y='226'/>
      <part name='047' x='267' y='227'/>
      <part name='048' x='277' y='236'/>
      <part name='049' x='290' y='241'/>
      <part name='050' x='241' y='209'/>
      <part name='051' x='243' y='219'/>
      <part name='052' x='243' y='229'/>
      <part name='053' x='242' y='240'/>
      <part name='054' x='239' y='250'/>
      <part name='055' x='249' y='268'/>
      <part name='056' x='257' y='209'/>
      <part name='057' x='255' y='219'/>
      <part name='058' x='254' y='230'/>
      <part name='059' x='255' y='240'/>
      <part name='060' x='257' y='251'/>
      <part name='061' x='229' y='250'/>
      <part name='062' x='226' y='256'/>
      <part name='063' x='226' y='264'/>
      <part name='064' x='233' y='268'/>
      <part name='065' x='232' y='262'/>
      <part name='066' x='268' y='251'/>
      <part name='067' x='271' y='257'/>
      <part name='068' x='271' y='264'/>
      <part name='069' x='264' y='268'/>
      <part name='070' x='265' y='263'/>
      <part name='071' x='181' y='206'/>
      <part name='072' x='187' y='195'/>
      <part name='073' x='197' y='189'/>
      <part name='074' x='213' y='189'/>
      <part name='075' x='233' y='195'/>
      <part name='076' x='232' y='202'/>
      <part name='077' x='267' y='202'/>
      <part name='078' x='265' y='195'/>
      <part name='079' x='285' y='189'/>
      <part name='080' x='300' y='189'/>
      <part name='081' x='310' y='196'/>
      <part name='082' x='318' y='207'/>
      <part name='083' x='195' y='200'/>
      <part name='084' x='211' y='198'/>
      <part name='085' x='287' y='199'/>
      <part name='086' x='302' y='200'/>
      <part name='087' x='218' y='297'/>
      <part name='088' x='229' y='289'/>
      <part name='089' x='239' y='285'/>
      <part name='090' x='248' y='287'/>
      <part name='091' x='258' y='285'/>
      <part name='092' x='269' y='290'/>
      <part name='093' x='278' y='297'/>
      <part name='094' x='230' y='296'/>
      <part name='095' x='239' y='295'/>
      <part name='096' x='248' y='296'/>
      <part name='097' x='258' y='295'/>
      <part name='098' x='268' y='296'/>
      <part name='099' x='230' y='296'/>
      <part name='100' x='239' y='295'/>
      <part name='101' x='248' y='296'/>
      <part name='102' x='259' y='295'/>
      <part name='103' x='268' y='296'/>
      <part name='104' x='227' y='303'/>
      <part name='105' x='237' y='307'/>
      <part name='106' x='249' y='308'/>
      <part name='107' x='261' y='307'/>
      <part name='108' x='271' y='303'/>
      <part name='109' x='165' y='226'/>
      <part name='110' x='166' y='252'/>
      <part name='111' x='170' y='281'/>
      <part name='112' x='331' y='228'/>
      <part name='113' x='330' y='255'/>
      <part name='114' x='326' y='283'/>
      <part name='115' x='150' y='218'/>
      <part name='116' x='146' y='233'/>
      <part name='117' x='148' y='252'/>
      <part name='118' x='152' y='269'/>
      <part name='119' x='162' y='282'/>
      <part name='120' x='348' y='221'/>
      <part name='121' x='351' y='236'/>
      <part name='122' x='348' y='254'/>
      <part name='123' x='344' y='270'/>
      <part name='124' x='334' y='284'/>
      <part name='125' x='174' y='299'/>
      <part name='126' x='180' y='316'/>
      <part name='127' x='200' y='336'/>
      <part name='128' x='222' y='350'/>
      <part name='129' x='249' y='354'/>
      <part name='130' x='276' y='349'/>
      <part name='131' x='299' y='336'/>
      <part name='132' x='316' y='318'/>
      <part name='133' x='323' y='301'/>
      <part name='134' x='170' y='196'/>
      <part name='135' x='177' y='171'/>
      <part name='136' x='184' y='147'/>
      <part name='137' x='200' y='133'/>
      <part name='138' x='224' y='129'/>
      <part name='139' x='249' y='131'/>
      <part name='140' x='275' y='130'/>
      <part name='141' x='298' y='135'/>
      <part name='142' x='314' y='149'/>
      <part name='143' x='321' y='172'/>
      <part name='144' x='328' y='197'/>
      <part name='145' x='182' y='358'/>
      <part name='146' x='149' y='303'/>
      <part name='147' x='135' y='223'/>
      <part name='148' x='146' y='172'/>
      <part name='149' x='169' y='133'/>
      <part name='150' x='202' y='105'/>
      <part name='151' x='249' y='93'/>
      <part name='152' x='299' y='108'/>
      <part name='153' x='331' y='137'/>
      <part name='154' x='353' y='177'/>
      <part name='155' x='362' y='226'/>
      <part name='156' x='349' y='305'/>
      <part name='157' x='315' y='358'/>
      <part name='158' x='220' y='267'/>
      <part name='159' x='212' y='277'/>
      <part name='160' x='207' y='289'/>
      <part name='161' x='279' y='267'/>
      <part name='162' x='286' y='278'/>
      <part name='163' x='291' y='290'/>
      <part name='164' x='176' y='238'/>
      <part name='165' x='188' y='248'/>
      <part name='166' x='205' y='253'/>
      <part name='167' x='322' y='240'/>
      <part name='168' x='310' y='249'/>
      <part name='169' x='295' y='254'/>
      <part name='170' x='241' y='271'/>
      <part name='171' x='240' y='280'/>
      <part name='172' x='255' y='271'/>
      <part name='173' x='257' y='280'/>
      <part name='174' x='249' y='329'/>
      <part name='175' x='249' y='340'/>
      <part name='176' x='235' y='321'/>
      <part name='177' x='249' y='318'/>
      <part name='178' x='263' y='321'/>
      <part name='179' x='242' y='263'/>
      <part name='180' x='245' y='267'/>
      <part name='181' x='253' y='267'/>
      <part name='182' x='255' y='264'/>
      <part name='183' x='222' y='384'/>
      <part name='184' x='277' y='384'/>
      <part name='185' x='165' y='239'/>
      <part name='186' x='168' y='267'/>
      <part name='187' x='332' y='241'/>
      <part name='188' x='328' y='268'/>
    </box>
  </image>
</images>
</dataset>
